nilearn/__init__.py
nilearn/_version.py
nilearn/conftest.py
nilearn/masking.py
nilearn/signal.py
nilearn/_utils/__init__.py
nilearn/_utils/cache_mixin.py
nilearn/_utils/class_inspect.py
nilearn/_utils/data_gen.py
nilearn/_utils/docs.py
nilearn/_utils/exceptions.py
nilearn/_utils/extmath.py
nilearn/_utils/fmriprep_confounds.py
nilearn/_utils/helpers.py
nilearn/_utils/logger.py
nilearn/_utils/masker_validation.py
nilearn/_utils/ndimage.py
nilearn/_utils/niimg.py
nilearn/_utils/niimg_conversions.py
nilearn/_utils/numpy_conversions.py
nilearn/_utils/param_validation.py
nilearn/_utils/path_finding.py
nilearn/_utils/segmentation.py
nilearn/_utils/testing.py
nilearn/_utils/tests/__init__.py
nilearn/_utils/tests/test_cache_mixin.py
nilearn/_utils/tests/test_class_inspect.py
nilearn/_utils/tests/test_common.py
nilearn/_utils/tests/test_data_gen.py
nilearn/_utils/tests/test_exceptions.py
nilearn/_utils/tests/test_extmath.py
nilearn/_utils/tests/test_helpers.py
nilearn/_utils/tests/test_logger.py
nilearn/_utils/tests/test_masker_validation.py
nilearn/_utils/tests/test_ndimage.py
nilearn/_utils/tests/test_niimg.py
nilearn/_utils/tests/test_niimg_conversions.py
nilearn/_utils/tests/test_numpy_conversions.py
nilearn/_utils/tests/test_param_validation.py
nilearn/_utils/tests/test_path_finding.py
nilearn/_utils/tests/test_segmentation.py
nilearn/_utils/tests/test_testing.py
nilearn/_utils/tests/data/__init__.py
nilearn/_utils/tests/data/mmap.dat
nilearn/_utils/tests/data/pymvpa-exampledata.tar.bz2
nilearn/connectome/__init__.py
nilearn/connectome/connectivity_matrices.py
nilearn/connectome/group_sparse_cov.py
nilearn/connectome/tests/__init__.py
nilearn/connectome/tests/test_connectivity_matrices.py
nilearn/connectome/tests/test_group_sparse_cov.py
nilearn/datasets/__init__.py
nilearn/datasets/_utils.py
nilearn/datasets/atlas.py
nilearn/datasets/func.py
nilearn/datasets/neurovault.py
nilearn/datasets/struct.py
nilearn/datasets/utils.py
nilearn/datasets/data/__init__.py
nilearn-0.11.0.dist-info/METADATA
nilearn-0.11.0.dist-info/WHEEL
nilearn-0.11.0.dist-info/licenses/AUTHORS.rst
nilearn-0.11.0.dist-info/licenses/LICENSE
nilearn-0.11.0.dist-info/RECORD
