Metadata-Version: 2.3
Name: nilearn
Version: 0.11.0
Summary: Statistical learning for neuroimaging in Python
Project-URL: Changelog, https://nilearn.github.io/stable/changes/whats_new.html
Project-URL: Development, https://github.com/nilearn/nilearn
Project-URL: Discussions, https://neurostars.org/tag/nilearn
Project-URL: Homepage, https://nilearn.github.io
Author: Nilearn developers
Maintainer-email: Bertrand Thirion <bertrand.thirion@inria.fr>
License: new BSD
Classifier: Intended Audience :: Developers
Classifier: Intended Audience :: Science/Research
Classifier: License :: OSI Approved
Classifier: Operating System :: MacOS
Classifier: Operating System :: Microsoft :: Windows
Classifier: Operating System :: POSIX
Classifier: Operating System :: Unix
Classifier: Programming Language :: C
Classifier: Programming Language :: Python
Classifier: Programming Language :: Python :: 3.9
Classifier: Programming Language :: Python :: 3.10
Classifier: Programming Language :: Python :: 3.11
Classifier: Programming Language :: Python :: 3.12
Classifier: Programming Language :: Python :: 3.13
Classifier: Topic :: Scientific/Engineering
Classifier: Topic :: Software Development
Requires-Python: >=3.9
Requires-Dist: joblib>=1.2.0
Requires-Dist: lxml
Requires-Dist: nibabel>=5.2.0
Requires-Dist: numpy>=1.22.4
Requires-Dist: packaging
Requires-Dist: pandas>=2.2.0
Requires-Dist: requests>=2.25.0
Requires-Dist: scikit-learn>=1.4.0
Requires-Dist: scipy>=1.8.0
Provides-Extra: dev
Requires-Dist: coverage; extra == 'dev'
Requires-Dist: furo; extra == 'dev'
Requires-Dist: kaleido; (platform_system != 'Windows') and extra == 'dev'
Requires-Dist: kaleido==0.1.0.post1; (platform_system == 'Windows') and extra == 'dev'
Requires-Dist: matplotlib>=3.3.0; extra == 'dev'
Requires-Dist: memory-profiler; extra == 'dev'
Requires-Dist: myst-parser; extra == 'dev'
Requires-Dist: numpydoc; extra == 'dev'
Requires-Dist: plotly; extra == 'dev'
Requires-Dist: pytest-cov; extra == 'dev'
Requires-Dist: pytest-randomly; extra == 'dev'
Requires-Dist: pytest-reporter-html1>=0.9.2; extra == 'dev'
Requires-Dist: pytest-xdist[psutil]; extra == 'dev'
Requires-Dist: pytest>=6.0.0; extra == 'dev'
Requires-Dist: ruamel-yaml; extra == 'dev'
Requires-Dist: sphinx; extra == 'dev'
Requires-Dist: sphinx-copybutton; extra == 'dev'
Requires-Dist: sphinx-design; extra == 'dev'
Requires-Dist: sphinx-gallery; extra == 'dev'
Requires-Dist: sphinxcontrib-bibtex; extra == 'dev'
Requires-Dist: sphinxext-opengraph; extra == 'dev'
Requires-Dist: tox; extra == 'dev'
Provides-Extra: doc
Requires-Dist: furo; extra == 'doc'
Requires-Dist: kaleido; (platform_system != 'Windows') and extra == 'doc'
Requires-Dist: kaleido==0.1.0.post1; (platform_system == 'Windows') and extra == 'doc'
Requires-Dist: matplotlib>=3.3.0; extra == 'doc'
Requires-Dist: memory-profiler; extra == 'doc'
Requires-Dist: myst-parser; extra == 'doc'
Requires-Dist: numpydoc; extra == 'doc'
Requires-Dist: plotly; extra == 'doc'
Requires-Dist: ruamel-yaml; extra == 'doc'
Requires-Dist: sphinx; extra == 'doc'
Requires-Dist: sphinx-copybutton; extra == 'doc'
Requires-Dist: sphinx-design; extra == 'doc'
Requires-Dist: sphinx-gallery; extra == 'doc'
Requires-Dist: sphinxcontrib-bibtex; extra == 'doc'
Requires-Dist: sphinxext-opengraph; extra == 'doc'
Provides-Extra: plotly
Requires-Dist: kaleido; (platform_system != 'Windows') and extra == 'plotly'
Requires-Dist: kaleido==0.1.0.post1; (platform_system == 'Windows') and extra == 'plotly'
Requires-Dist: matplotlib>=3.3.0; extra == 'plotly'
Requires-Dist: plotly; extra == 'plotly'
Provides-Extra: plotting
Requires-Dist: kaleido; (platform_system != 'Windows') and extra == 'plotting'
Requires-Dist: kaleido==0.1.0.post1; (platform_system == 'Windows') and extra == 'plotting'
Requires-Dist: matplotlib>=3.3.0; extra == 'plotting'
Requires-Dist: plotly; extra == 'plotting'
Provides-Extra: style
Requires-Dist: tox; extra == 'style'
Provides-Extra: test
Requires-Dist: coverage; extra == 'test'
Requires-Dist: pytest-cov; extra == 'test'
Requires-Dist: pytest-randomly; extra == 'test'
Requires-Dist: pytest-reporter-html1>=0.9.2; extra == 'test'
Requires-Dist: pytest-xdist[psutil]; extra == 'test'
Requires-Dist: pytest>=6.0.0; extra == 'test'
Requires-Dist: tox; extra == 'test'
